<BackupInst xmlns="http://www.microsoft.com/GroupPolicy/GPOOperations/Manifest"><GPOGuid><![CDATA[{29206583-598E-43C3-BF5F-4AE10D7756F4}]]></GPOGuid><GPODomain><![CDATA[Int.Raudz.Com]]></GPODomain><GPODomainGuid><![CDATA[{0e01247d-66c9-4c05-8a39-9a6da8240a8d}]]></GPODomainGuid><GPODomainController><![CDATA[DC01-Kelowna.Int.Raudz.Com]]></GPODomainController><BackupTime><![CDATA[2022-03-26T14:50:33]]></BackupTime><ID><![CDATA[{1FA5CC1F-8A89-4C41-B026-414DCD30968C}]]></ID><Comment><![CDATA[]]></Comment><GPODisplayName><![CDATA[Executives Wallpaper]]></GPODisplayName></BackupInst>
